azureml/__init__.py
azureml/acft/__init__.py
azureml/acft/common_components/__init__.py
azureml/acft/common_components/_version.py
azureml/acft/common_components/image/__init__.py
azureml/acft/common_components/image/runtime_common/__init__.py
azureml/acft/common_components/image/runtime_common/classification/__init__.py
azureml/acft/common_components/image/runtime_common/classification/common/__init__.py
azureml/acft/common_components/image/runtime_common/classification/common/classification_utils.py
azureml/acft/common_components/image/runtime_common/classification/common/constants.py
azureml/acft/common_components/image/runtime_common/classification/common/transforms.py
azureml/acft/common_components/image/runtime_common/classification/io/__init__.py
azureml/acft/common_components/image/runtime_common/classification/io/read/__init__.py
azureml/acft/common_components/image/runtime_common/classification/io/read/dataloader.py
azureml/acft/common_components/image/runtime_common/classification/io/read/dataset_wrappers.py
azureml/acft/common_components/image/runtime_common/classification/io/read/utils.py
azureml/acft/common_components/image/runtime_common/classification/models/__init__.py
azureml/acft/common_components/image/runtime_common/classification/models/base_model_wrapper.py
azureml/acft/common_components/image/runtime_common/common/__init__.py
azureml/acft/common_components/image/runtime_common/common/aml_dataset_base_wrapper.py
azureml/acft/common_components/image/runtime_common/common/artifacts_utils.py
azureml/acft/common_components/image/runtime_common/common/average_meter.py
azureml/acft/common_components/image/runtime_common/common/base_model_factory.py
azureml/acft/common_components/image/runtime_common/common/base_model_settings.py
azureml/acft/common_components/image/runtime_common/common/constants.py
azureml/acft/common_components/image/runtime_common/common/data_utils.py
azureml/acft/common_components/image/runtime_common/common/dataloaders.py
azureml_acft_common_components-47.0.0.dist-info/LICENSE.txt
azureml_acft_common_components-47.0.0.dist-info/METADATA
azureml_acft_common_components-47.0.0.dist-info/WHEEL
azureml_acft_common_components-47.0.0.dist-info/namespace_packages.txt
azureml_acft_common_components-47.0.0.dist-info/top_level.txt
azureml_acft_common_components-47.0.0.dist-info/RECORD
